app/__init__.py
app/calculate_coco_features.py
app/caption.py
app/classification.py
app/dataset_browser.py
app/image_text_match.py
app/main.py
app/multimodal_search.py
app/multipage.py
app/text_localization.py
app/utils.py
app/vqa.py
docs/conf.py
lavis/__init__.py
lavis/common/config.py
lavis/common/dist_utils.py
lavis/common/gradcam.py
lavis/common/logger.py
lavis/common/optims.py
lavis/common/registry.py
lavis/common/utils.py
lavis/common/vqa_tools/__init__.py
lavis/common/vqa_tools/vqa.py
lavis/common/vqa_tools/vqa_eval.py
lavis/configs/default.yaml
lavis/configs/datasets/aokvqa/defaults.yaml
lavis/configs/datasets/avsd/defaults_dial.yaml
lavis/configs/datasets/coco/defaults_cap.yaml
lavis/configs/datasets/coco/defaults_ret.yaml
lavis/configs/datasets/coco/defaults_vqa.yaml
lavis/configs/datasets/coco/eval_vqa.yaml
lavis/configs/datasets/conceptual_caption/defaults_12m.yaml
lavis/configs/datasets/conceptual_caption/defaults_3m.yaml
lavis/configs/datasets/didemo/defaults_ret.yaml
lavis/configs/datasets/flickr30k/defaults.yaml
lavis/configs/datasets/gqa/balanced_testdev.yaml
lavis/configs/datasets/gqa/balanced_val.yaml
lavis/configs/datasets/gqa/defaults.yaml
lavis/configs/datasets/imagenet/defaults.yaml
lavis/configs/datasets/laion/defaults_2B_multi.yaml
lavis/configs/datasets/msrvtt/defaults_cap.yaml
lavis/configs/datasets/msrvtt/defaults_qa.yaml
lavis/configs/datasets/msrvtt/defaults_ret.yaml
lavis/configs/datasets/msvd/defaults_cap.yaml
lavis/configs/datasets/msvd/defaults_qa.yaml
lavis/configs/datasets/nlvr/defaults.yaml
lavis/configs/datasets/nocaps/defaults.yaml
lavis/configs/datasets/okvqa/defaults.yaml
lavis/configs/datasets/sbu_caption/defaults.yaml
lavis/configs/datasets/snli_ve/defaults.yaml
lavis/configs/datasets/vatex/defaults_cap.yaml
lavis/configs/datasets/vg/defaults_caption.yaml
lavis/configs/datasets/vg/defaults_vqa.yaml
lavis/configs/models/albef_classification_ve.yaml
lavis/configs/models/albef_feature_extractor.yaml
salesforce_lavis-1.0.2.dist-info/LICENSE.txt
salesforce_lavis-1.0.2.dist-info/METADATA
salesforce_lavis-1.0.2.dist-info/WHEEL
salesforce_lavis-1.0.2.dist-info/top_level.txt
salesforce_lavis-1.0.2.dist-info/RECORD
